{
  "UseCustom": true,
  "TitleFore":          "#{{colors.on_background.default.hex_stripped}}",
  "TitleBack":          "#{{colors.primary.default.hex_stripped}}",
  "TitleInfo":          "#{{colors.primary.default.hex_stripped | set_lightness: -7.5}}",
  "NormalTitle":        "#{{colors.on_background.default.hex_stripped}}",
  "DimmedTitle":        "#{{colors.on_surface_variant.default.hex_stripped}}",
  "SelectedTitle":      "#{{colors.primary_fixed.default.hex_stripped | set_lightness: -7.5}}",
  "NormalDesc":         "#{{colors.on_surface_variant.default.hex_stripped}}",
  "DimmedDesc":         "#{{colors.on_surface_variant.default.hex_stripped}}",
  "SelectedDesc":       "#{{colors.primary_fixed.default.hex_stripped | set_lightness: -7.5}}",
  "StatusMsg":          "#{{colors.primary.default.hex_stripped | set_lightness: -5.0}}",
  "PinIndicatorColor":  "#{{colors.primary_fixed.default.hex_stripped | set_lightness: -2.5}}",
  "SelectedBorder":     "#{{colors.primary.default.hex_stripped | set_lightness: -7.5}}",
  "SelectedDescBorder": "#{{colors.primary.default.hex_stripped | set_lightness: -7.5}}",
  "FilteredMatch":      "#{{colors.on_background.default.hex_stripped}}",
  "FilterPrompt":       "#{{colors.primary.default.hex_stripped | set_lightness: -5.0}}",
  "FilterInfo":         "#{{colors.primary.default.hex_stripped | set_lightness: -7.5}}",
  "FilterText":         "#{{colors.on_background.default.hex_stripped}}",
  "FilterCursor":       "#{{colors.primary_fixed.default.hex_stripped | set_lightness: -2.5}}",
  "HelpKey":            "#{{colors.on_surface_variant.default.hex_stripped}}",
  "HelpDesc":           "#{{colors.on_surface_variant.default.hex_stripped}}",
  "PageActiveDot":      "#{{colors.primary.default.hex_stripped | set_lightness: -7.5}}",
  "PageInactiveDot":    "#{{colors.on_surface_variant.default.hex_stripped}}",
  "DividerDot":         "#{{colors.primary.default.hex_stripped | set_lightness: -7.5}}",
  "PreviewedText":      "#{{colors.on_background.default.hex_stripped}}",
  "PreviewBorder":      "#{{colors.primary.default.hex_stripped | set_lightness: -7.5}}"
}

